automatic_youtube_maker_story/__init__.py
automatic_youtube_maker_story/audio/__init__.py
automatic_youtube_maker_story/audio/TextToSpeak.py
automatic_youtube_maker_story/audio/TextToSpeakQuiz.py
automatic_youtube_maker_story/config/config.json
automatic_youtube_maker_story/Editor/__init__.py
automatic_youtube_maker_story/Editor/pipeToMaker.py
automatic_youtube_maker_story/extra_model_paths.yaml
automatic_youtube_maker_story/historiaInfantil.py
automatic_youtube_maker_story/history/__init__.py
automatic_youtube_maker_story/history/TextToHistory.py
automatic_youtube_maker_story/install_packeges.py
automatic_youtube_maker_story/install_packeges_linux.py
automatic_youtube_maker_story/utils/__init__.py
automatic_youtube_maker_story/utils/path_control.py
automatic_youtube_maker_story/utils/run_history_infantil.ps1
automatic_youtube_maker_story/utils/run_history_infantil.sh
automatic_youtube_maker_story/utils/server_comfy.ps1
automatic_youtube_maker_story/utils/server_comfy.sh
automatic_youtube_maker_story/utils/teste_run.ps1
automatic_youtube_maker_story/utils/teste_run.sh
automatic_youtube_maker_story/video/__init__.py
automatic_youtube_maker_story/video/TextToImageSquad.py
automatic_youtube_maker_story/video/TextToVideo16x9.py
automatic_youtube_maker_story/video/TextToVideo16x9Tests.py
automatic_youtube_maker_story/youtube/upload.py
automatic_youtube_maker_story-0.5.dist-info/METADATA
automatic_youtube_maker_story-0.5.dist-info/WHEEL
automatic_youtube_maker_story-0.5.dist-info/RECORD
