Metadata-Version: 2.3
Name: automatic-youtube-maker-story
Version: 0.5
Summary: Gerador de video de 1 minuto automático, utilizando ComfyUI, narration-xtts2, story-children-video-maker e story-chilren-gemma3
Author: William Ferreira Linux
Author-email: williambox37@gmail.com
Requires-Python: >=3.11,<4.0
Classifier: Programming Language :: Python :: 3
Classifier: Programming Language :: Python :: 3.11
Classifier: Programming Language :: Python :: 3.12
Classifier: Programming Language :: Python :: 3.13
Requires-Dist: accelerate (>=1.7.0,<2.0.0)
Requires-Dist: apiclient (>=1.0.4,<2.0.0)
Requires-Dist: einops (>=0.8.1,<0.9.0)
Requires-Dist: gitpython (>=3.1.44,<4.0.0)
Requires-Dist: google-api-python-client (>=2.169.0,<3.0.0)
Requires-Dist: google-auth-httplib2 (>=0.2.0,<0.3.0)
Requires-Dist: google-auth-oauthlib (>=1.2.2,<2.0.0)
Requires-Dist: httplib2 (>=0.22.0,<0.23.0)
Requires-Dist: imageio-ffmpeg (>=0.6.0,<0.7.0)
Requires-Dist: narration-xtts2 (>=1.0.6,<2.0.0)
Requires-Dist: oauth2client (>=4.1.3,<5.0.0)
Requires-Dist: opencv-python (>=4.11.0.86,<5.0.0.0)
Requires-Dist: pyyaml (>=6.0.2,<7.0.0)
Requires-Dist: requests (>=2.32.3,<3.0.0)
Requires-Dist: sageattention (>=1.0.6,<2.0.0)
Requires-Dist: story-children-video-maker (>=0.1.2,<0.2.0)
Requires-Dist: story-chilren-gemma3 (>=0.1.21,<0.2.0)
Requires-Dist: torch (>=2.3,<2.4)
Requires-Dist: torchaudio (>=2.3,<2.4)
Requires-Dist: torchvision (>=0.18,<0.19)
Project-URL: Homepage, https://github.com/illiamw/illiamw
